fhirspec.py
fhirspec-0.6.0.dist-info/WHEEL
fhirspec-0.6.0.dist-info/METADATA
fhirspec-0.6.0.dist-info/RECORD
