Metadata-Version: 2.4
Name: fhirspec
Version: 0.6.0
Summary: Python representation of FHIR® https://www.hl7.org/fhir/ specification.
Home-page: https://github.com/nazrulworld/fhirspec
Author: Md Nazrul Islam
Author-email: email2nazrul@gmail.com
Requires-Python: >=3.6
Classifier: Intended Audience :: Information Technology
Classifier: Intended Audience :: Healthcare Industry
Classifier: Operating System :: OS Independent
Classifier: Topic :: Software Development :: Libraries :: Python Modules
Classifier: Topic :: Software Development :: Libraries
Classifier: Topic :: Software Development
Classifier: Typing :: Typed
Classifier: Development Status :: 4 - Beta
Classifier: Environment :: Web Environment
Classifier: Intended Audience :: Developers
Classifier: License :: OSI Approved :: MIT License
Classifier: Programming Language :: Python
Classifier: Programming Language :: Python :: 3
Classifier: Programming Language :: Python :: 3 :: Only
Classifier: Programming Language :: Python :: 3.6
Classifier: Programming Language :: Python :: 3.7
Classifier: Programming Language :: Python :: 3.8
Classifier: Programming Language :: Python :: 3.9
Classifier: Programming Language :: Python :: 3.10
Classifier: Programming Language :: Python :: 3.11
Classifier: Programming Language :: Python :: 3.12
Classifier: Programming Language :: Python :: 3.13
Requires-Dist: setuptools
Requires-Dist: pytest ; extra == "all"
Requires-Dist: pytest-cov ; extra == "all"
Requires-Dist: mypy ; extra == "all"
Requires-Dist: black>=23.0,<24.0 ; extra == "all" and ( python_version >= '3.7')
Requires-Dist: black==22.8.0 ; extra == "all" and ( python_version < '3.7')
Requires-Dist: isort ; extra == "all"
Requires-Dist: autoflake ; extra == "all"
Requires-Dist: flake8 ; extra == "all"
Requires-Dist: vulture ; extra == "all"
Requires-Dist: pytoml ; extra == "all"
Requires-Dist: json5 ; extra == "all"
Requires-Dist: autoflake ; extra == "dev"
Requires-Dist: vulture ; extra == "dev"
Requires-Dist: json5 ; extra == "dev"
Requires-Dist: pytest ; extra == "test"
Requires-Dist: pytest-cov ; extra == "test"
Requires-Dist: mypy ; extra == "test"
Requires-Dist: black>=23.0,<24.0 ; extra == "test" and ( python_version >= '3.7')
Requires-Dist: black==22.8.0 ; extra == "test" and ( python_version < '3.7')
Requires-Dist: isort ; extra == "test"
Requires-Dist: flake8 ; extra == "test"
Requires-Dist: pytoml ; extra == "toml"
Project-URL: Documentation, https://nazrul.me/fhirspec/
Provides-Extra: all
Provides-Extra: dev
Provides-Extra: test
Provides-Extra: toml
